Workbook

Sheet Dashboard
A1: NimbusEdge Technologies — Corporate Financial Performance Dashboard
A2: FY2024–FY2025 | Prepared by FP&A | All figures in USD
A4: FILTERS (use Excel slicers on Raw_Data table for live filtering)
A5: Month | B5: Quarter | C5: Year | D5: Region | E5: Department / Product
A7: TOTAL REVENUE | C7: GROSS PROFIT | E7: EBITDA | G7: NET PROFIT | I7: GROSS MARGIN % | K7: NET MARGIN %
A8: =KPI_Summary!B6 -> 14602052 | C8: =KPI_Summary!B8 -> 10621504 | E8: =KPI_Summary!B10 -> 6242117.8 | G8: =KPI_Summary!B12 -> 4039531.2 | I8: =KPI_Summary!B9 -> 0.72739802 | K8: =KPI_Summary!B13 -> 0.27664133
A10: Revenue, Cost & Profitability Trends
A29: Region, Department & Working Capital Analysis

Sheet Raw_Data
A1: Date | B1: Month | C1: Quarter | D1: Year | E1: Department | F1: Region | G1: Product_Category | H1: Cost_Center | I1: Revenue | J1: COGS | K1: Gross_Profit | L1: Operating_Expenses | M1: EBITDA | N1: Depreciation | O1: Interest_Expense | P1: Tax_Expense | Q1: Net_Profit | R1: Gross_Margin_Pct | S1: EBITDA_Margin_Pct | T1: Net_Profit_Margin_Pct | U1: Budgeted_Revenue | V1: Actual_Revenue | W1: Budgeted_Expense | X1: Actual_Expense | Y1: Budget_Variance | Z1: Accounts_Receivable | AA1: Accounts_Payable | AB1: Cash_Balance | AC1: Working_Capital
A2: 45292 | B2: Jan | C2: Q1 | D2: 2024 | E2: Sales | F2: North America | G2: Core Subscription | H2: SAL-NO-01 | I2: 193060.07 | J2: 42957.87 | K2: =I2-J2 -> 150102.2 | L2: 57877.15 | M2: =K2-L2 -> 92225.05 | N2: 6757.1 | O2: 4100.78 | P2: 19528.12 | Q2: =M2-N2-O2-P2 -> 61839.05 | R2: =IFERROR(K2/I2,0) -> 0.77748962 | S2: =IFERROR(M2/I2,0) -> 0.47770132 | T2: =IFERROR(Q2/I2,0) -> 0.32030989 | U2: 185000 | V2: =I2 -> 193060.07 | W2: 96200 | X2: =J2+L2 -> 100835.02 | Y2: =V2-U2 -> 8060.07 | Z2: 280884.09 | AA2: 61035.12 | AB2: 231075.74 | AC2: =Z2-AA2 -> 219848.97
A3: 45323 | B3: Feb | C3: Q1 | D3: 2024 | E3: Sales | F3: North America | G3: Core Subscription | H3: SAL-NO-01 | I3: 188785.64 | J3: 42409.93 | K3: =I3-J3 -> 146375.71 | L3: 61239.74 | M3: =K3-L3 -> 85135.97 | N3: 6607.5 | O3: 4009.61 | P3: 17884.53 | Q3: =M3-N3-O3-P3 -> 56634.33 | R3: =IFERROR(K3/I3,0) -> 0.77535405 | S3: =IFERROR(M3/I3,0) -> 0.45096634 | T3: =IFERROR(Q3/I3,0) -> 0.29999279 | U3: 187590 | V3: =I3 -> 188785.64 | W3: 97546.8 | X3: =J3+L3 -> 103649.67 | Y3: =V3-U3 -> 1195.64 | Z3: 265487.7 | AA3: 65480.5 | AB3: 232510.76 | AC3: =Z3-AA3 -> 200007.2
A4: 45352 | B4: Mar | C4: Q1 | D4: 2024 | E4: Sales | F4: North America | G4: Core Subscription | H4: SAL-NO-01 | I4: 174085.32 | J4: 34926.55 | K4: =I4-J4 -> 139158.77 | L4: 64017.78 | M4: =K4-L4 -> 75140.99 | N4: 6092.99 | O4: 4173.67 | P4: 15569.84 | Q4: =M4-N4-O4-P4 -> 49304.49 | R4: =IFERROR(K4/I4,0) -> 0.79937108 | S4: =IFERROR(M4/I4,0) -> 0.43163312 | T4: =IFERROR(Q4/I4,0) -> 0.28322026 | U4: 190216.26 | V4: =I4 -> 174085.32 | W4: 98912.46 | X4: =J4+L4 -> 98944.33 | Y4: =V4-U4 -> -16130.94 | Z4: 239826.04 | AA4: 67993.46 | AB4: 237502.32 | AC4: =Z4-AA4 -> 171832.58
A5: 45383 | B5: Apr | C5: Q2 | D5: 2024 | E5: Sales | F5: North America | G5: Core Subscription | H5: SAL-NO-01 | I5: 190326.6 | J5: 43305.39 | K5: =I5-J5 -> 147021.21 | L5: 59511.55 | M5: =K5-L5 -> 87509.66 | N5: 6661.43 | O5: 4544.24 | P5: 18312.96 | Q5: =M5-N5-O5-P5 -> 57991.03 | R5: =IFERROR(K5/I5,0) -> 0.77246801 | S5: =IFERROR(M5/I5,0) -> 0.45978681 | T5: =IFERROR(Q5/I5,0) -> 0.3046922 | U5: 192879.29 | V5: =I5 -> 190326.6 | W5: 100297.23 | X5: =J5+L5 -> 102816.94 | Y5: =V5-U5 -> -2552.69 | Z5: 272578.61 | AA5: 65699.86 | AB5: 233164.47 | AC5: =Z5-AA5 -> 206878.75
A6: 45413 | B6: May | C6: Q2 | D6: 2024 | E6: Sales | F6: North America | G6: Core Subscription | H6: SAL-NO-01 | I6: 205922.22 | J6: 44627.56 | K6: =I6-J6 -> 161294.66 | L6: 51238.73 | M6: =K6-L6 -> 110055.93 | N6: 7207.28 | O6: 3902.97 | P6: 23746.96 | Q6: =M6-N6-O6-P6 -> 75198.72 | R6: =IFERROR(K6/I6,0) -> 0.78327953 | S6: =IFERROR(M6/I6,0) -> 0.53445388 | T6: =IFERROR(Q6/I6,0) -> 0.36518021 | U6: 195579.6 | V6: =I6 -> 205922.22 | W6: 101701.39 | X6: =J6+L6 -> 95866.29 | Y6: =V6-U6 -> 10342.62 | Z6: 298718.8 | AA6: 56798.58 | AB6: 233694.95 | AC6: =Z6-AA6 -> 241920.22
A7: 45444 | B7: Jun | C7: Q2 | D7: 2024 | E7: Sales | F7: North America | G7: Core Subscription | H7: SAL-NO-01 | I7: 195112.01 | J7: 43371.14 | K7: =I7-J7 -> 151740.87 | L7: 63343.15 | M7: =K7-L7 -> 88397.72 | N7: 6828.92 | O7: 2143.4 | P7: 19062.1 | Q7: =M7-N7-O7-P7 -> 60363.3 | R7: =IFERROR(K7/I7,0) -> 0.77771158 | S7: =IFERROR(M7/I7,0) -> 0.4530614 | T7: =IFERROR(Q7/I7,0) -> 0.30937767 | U7: 198317.71 | V7: =I7 -> 195112.01 | W7: 103125.21 | X7: =J7+L7 -> 106714.29 | Y7: =V7-U7 -> -3205.7 | Z7: 267092.01 | AA7: 70622.88 | AB7: 236265.05 | AC7: =Z7-AA7 -> 196469.13
A8: 45474 | B8: Jul | C8: Q3 | D8: 2024 | E8: Sales | F8: North America | G8: Core Subscription | H8: SAL-NO-01 | I8: 194069.33 | J8: 45497.48 | K8: =I8-J8 -> 148571.85 | L8: 61825.42 | M8: =K8-L8 -> 86746.43 | N8: 6792.43 | O8: 4984.63 | P8: 17992.65 | Q8: =M8-N8-O8-P8 -> 56976.72 | R8: =IFERROR(K8/I8,0) -> 0.76556069 | S8: =IFERROR(M8/I8,0) -> 0.44698681 | T8: =IFERROR(Q8/I8,0) -> 0.29358951 | U8: 201094.16 | V8: =I8 -> 194069.33 | W8: 104568.96 | X8: =J8+L8 -> 107322.9 | Y8: =V8-U8 -> -7024.83 | Z8: 275719.14 | AA8: 68750.14 | AB8: 240841.38 | AC8: =Z8-AA8 -> 206969
A9: 45505 | B9: Aug | C9: Q3 | D9: 2024 | E9: Sales | F9: North America | G9: Core Subscription | H9: SAL-NO-01 | I9: 219855.56 | J9: 50591.81 | K9: =I9-J9 -> 169263.75 | L9: 65963.2 | M9: =K9-L9 -> 103300.55 | N9: 7694.94 | O9: 3693.63 | P9: 22058.88 | Q9: =M9-N9-O9-P9 -> 69853.1 | R9: =IFERROR(K9/I9,0) -> 0.76988615 | S9: =IFERROR(M9/I9,0) -> 0.46985644 | T9: =IFERROR(Q9/I9,0) -> 0.31772269 | U9: 203909.48 | V9: =I9 -> 219855.56 | W9: 106032.93 | X9: =J9+L9 -> 116555.01 | Y9: =V9-U9 -> 15946.08 | Z9: 313480.17 | AA9: 75047.24 | AB9: 241351.84 | AC9: =Z9-AA9 -> 238432.93
A10: 45536 | B10: Sep | C10: Q3 | D10: 2024 | E10: Sales | F10: North America | G10: Core Subscription | H10: SAL-NO-01 | I10: 208098.24 | J10: 42819.6 | K10: =I10-J10 -> 165278.64 | L10: 65728.09 | M10: =K10-L10 -> 99550.55 | N10: 7283.44 | O10: 2710.32 | P10: 21493.63 | Q10: =M10-N10-O10-P10 -> 68063.16 | R10: =IFERROR(K10/I10,0) -> 0.79423372 | S10: =IFERROR(M10/I10,0) -> 0.47838247 | T10: =IFERROR(Q10/I10,0) -> 0.32707225 | U10: 206764.21 | V10: =I10 -> 208098.24 | W10: 107517.39 | X10: =J10+L10 -> 108547.69 | Y10: =V10-U10 -> 1334.03 | Z10: 282917.38 | AA10: 75503.18 | AB10: 245309.85 | AC10: =Z10-AA10 -> 207414.2
A11: 45566 | B11: Oct | C11: Q4 | D11: 2024 | E11: Sales | F11: North America | G11: Core Subscription | H11: SAL-NO-01 | I11: 202631.73 | J11: 42302.22 | K11: =I11-J11 -> 160329.51 | L11: 60259.33 | M11: =K11-L11 -> 100070.18 | N11: 7092.11 | O11: 2700.59 | P11: 21666.6 | Q11: =M11-N11-O11-P11 -> 68610.88 | R11: =IFERROR(K11/I11,0) -> 0.79123595 | S11: =IFERROR(M11/I11,0) -> 0.49385247 | T11: =IFERROR(Q11/I11,0) -> 0.3385989 | U11: 209658.91 | V11: =I11 -> 202631.73 | W11: 109022.63 | X11: =J11+L11 -> 102561.55 | Y11: =V11-U11 -> -7027.18 | Z11: 276496.64 | AA11: 66692.04 | AB11: 243510.1 | AC11: =Z11-AA11 -> 209804.6
A12: 45597 | B12: Nov | C12: Q4 | D12: 2024 | E12: Sales | F12: North America | G12: Core Subscription | H12: SAL-NO-01 | I12: 211354.67 | J12: 52083.11 | K12: =I12-J12 -> 159271.56 | L12: 66607.24 | M12: =K12-L12 -> 92664.32 | N12: 7397.41 | O12: 2545.69 | P12: 19853.09 | Q12: =M12-N12-O12-P12 -> 62868.13 | R12: =IFERROR(K12/I12,0) -> 0.75357483 | S12: =IFERROR(M12/I12,0) -> 0.43843044 | T12: =IFERROR(Q12/I12,0) -> 0.29745323 | U12: 212594.13 | V12: =I12 -> 211354.67 | W12: 110548.95 | X12: =J12+L12 -> 118690.35 | Y12: =V12-U12 -> -1239.46 | Z12: 310618.5 | AA12: 73337.76 | AB12: 245757.03 | AC12: =Z12-AA12 -> 237280.74
A13: 45627 | B13: Dec | C13: Q4 | D13: 2024 | E13: Sales | F13: North America | G13: Core Subscription | H13: SAL-NO-01 | I13: 217561.96 | J13: 52583.6 | K13: =I13-J13 -> 164978.36 | L13: 68804.07 | M13: =K13-L13 -> 96174.29 | N13: 7614.67 | O13: 2015.99 | P13: 20770.47 | Q13: =M13-N13-O13-P13 -> 65773.16 | R13: =IFERROR(K13/I13,0) -> 0.75830517 | S13: =IFERROR(M13/I13,0) -> 0.44205471 | T13: =IFERROR(Q13/I13,0) -> 0.30231921 | U13: 215570.45 | V13: =I13 -> 217561.96 | W13: 112096.64 | X13: =J13+L13 -> 121387.67 | Y13: =V13-U13 -> 1991.51 | Z13: 300981.02 | AA13: 79439.35 | AB13: 241771.13 | AC13: =Z13-AA13 -> 221541.67
... A121: 45992 | B121: Dec | C121: Q4 | D121: 2025 | E121: Sales | F121: APAC | G121: Core Subscription | H121: SAL-AP-05 | I121: 141132.63 | J121: 32644.2 | K121: =I121-J121 -> 108488.43 | L121: 44251.27 | M121: =K121-L121 -> 64237.16 | N121: 4516.24 | O121: 4596.22 | P121: 13229.93 | Q121: =M121-N121-O121-P121 -> 41894.77 | R121: =IFERROR(K121/I121,0) -> 0.76869842 | S121: =IFERROR(M121/I121,0) -> 0.45515456 | T121: =IFERROR(Q121/I121,0) -> 0.2968468 | U121: 140296.75 | V121: =I121 -> 141132.63 | W121: 79969.15 | X121: =J121+L121 -> 76895.47 | Y121: =V121-U121 -> 835.88 | Z121: 245577.64 | AA121: 56690.87 | AB121: 230909.62 | AC121: =Z121-AA121 -> 188886.77

Sheet Revenue_Analysis
A1: Revenue Analysis
A2: Source: Raw_Data (SUMIFS-driven, recalculates automatically)
A4: Monthly Revenue Trend
A5: Month | B5: Actual Revenue | C5: Budgeted Revenue | D5: Revenue Variance | E5: Variance % | F5: MoM Growth %
A6: 45292 | B6: =SUMIFS(Raw_Data!$I:$I,Raw_Data!$A:$A,A6) -> 504838.69 | C6: =SUMIFS(Raw_Data!$U:$U,Raw_Data!$A:$A,A6) -> 526000 | D6: =B6-C6 -> -21161.31 | E6: =IFERROR(D6/C6,0) -> -0.040230627 | F6: 0
A7: 45323 | B7: =SUMIFS(Raw_Data!$I:$I,Raw_Data!$A:$A,A7) -> 524248.16 | C7: =SUMIFS(Raw_Data!$U:$U,Raw_Data!$A:$A,A7) -> 532823 | D7: =B7-C7 -> -8574.84 | E7: =IFERROR(D7/C7,0) -> -0.016093224 | F7: =IFERROR((B7-B6)/B6,0) -> 0.038446875
A8: 45352 | B8: =SUMIFS(Raw_Data!$I:$I,Raw_Data!$A:$A,A8) -> 525250.21 | C8: =SUMIFS(Raw_Data!$U:$U,Raw_Data!$A:$A,A8) -> 539740.74 | D8: =B8-C8 -> -14490.53 | E8: =IFERROR(D8/C8,0) -> -0.026847204 | F8: =IFERROR((B8-B7)/B7,0) -> 0.0019114039
A9: 45383 | B9: =SUMIFS(Raw_Data!$I:$I,Raw_Data!$A:$A,A9) -> 532310.19 | C9: =SUMIFS(Raw_Data!$U:$U,Raw_Data!$A:$A,A9) -> 546754.65 | D9: =B9-C9 -> -14444.46 | E9: =IFERROR(D9/C9,0) -> -0.026418541 | F9: =IFERROR((B9-B8)/B8,0) -> 0.013441175
A10: 45413 | B10: =SUMIFS(Raw_Data!$I:$I,Raw_Data!$A:$A,A10) -> 566263.09 | C10: =SUMIFS(Raw_Data!$U:$U,Raw_Data!$A:$A,A10) -> 553866.1 | D10: =B10-C10 -> 12396.99 | E10: =IFERROR(D10/C10,0) -> 0.022382648 | F10: =IFERROR((B10-B9)/B9,0) -> 0.06378405
A11: 45444 | B11: =SUMIFS(Raw_Data!$I:$I,Raw_Data!$A:$A,A11) -> 564664.02 | C11: =SUMIFS(Raw_Data!$U:$U,Raw_Data!$A:$A,A11) -> 561076.56 | D11: =B11-C11 -> 3587.46 | E11: =IFERROR(D11/C11,0) -> 0.0063938868 | F11: =IFERROR((B11-B10)/B10,0) -> -0.0028238994
A12: 45474 | B12: =SUMIFS(Raw_Data!$I:$I,Raw_Data!$A:$A,A12) -> 548537.48 | C12: =SUMIFS(Raw_Data!$U:$U,Raw_Data!$A:$A,A12) -> 568387.51 | D12: =B12-C12 -> -19850.03 | E12: =IFERROR(D12/C12,0) -> -0.03492341 | F12: =IFERROR((B12-B11)/B11,0) -> -0.028559532
A13: 45505 | B13: =SUMIFS(Raw_Data!$I:$I,Raw_Data!$A:$A,A13) -> 578593.82 | C13: =SUMIFS(Raw_Data!$U:$U,Raw_Data!$A:$A,A13) -> 575800.41 | D13: =B13-C13 -> 2793.41 | E13: =IFERROR(D13/C13,0) -> 0.0048513512 | F13: =IFERROR((B13-B12)/B12,0) -> 0.054793594
A14: 45536 | B14: =SUMIFS(Raw_Data!$I:$I,Raw_Data!$A:$A,A14) -> 589255.99 | C14: =SUMIFS(Raw_Data!$U:$U,Raw_Data!$A:$A,A14) -> 583316.78 | D14: =B14-C14 -> 5939.21 | E14: =IFERROR(D14/C14,0) -> 0.010181792 | F14: =IFERROR((B14-B13)/B13,0) -> 0.018427729
A15: 45566 | B15: =SUMIFS(Raw_Data!$I:$I,Raw_Data!$A:$A,A15) -> 566698.07 | C15: =SUMIFS(Raw_Data!$U:$U,Raw_Data!$A:$A,A15) -> 590938.16 | D15: =B15-C15 -> -24240.09 | E15: =IFERROR(D15/C15,0) -> -0.041019673 | F15: =IFERROR((B15-B14)/B14,0) -> -0.038282038
A16: 45597 | B16: =SUMIFS(Raw_Data!$I:$I,Raw_Data!$A:$A,A16) -> 582586.05 | C16: =SUMIFS(Raw_Data!$U:$U,Raw_Data!$A:$A,A16) -> 598666.1 | D16: =B16-C16 -> -16080.05 | E16: =IFERROR(D16/C16,0) -> -0.026859797 | F16: =IFERROR((B16-B15)/B15,0) -> 0.028036058
A17: 45627 | B17: =SUMIFS(Raw_Data!$I:$I,Raw_Data!$A:$A,A17) -> 621348.63 | C17: =SUMIFS(Raw_Data!$U:$U,Raw_Data!$A:$A,A17) -> 606502.2 | D17: =B17-C17 -> 14846.43 | E17: =IFERROR(D17/C17,0) -> 0.024478774 | F17: =IFERROR((B17-B16)/B16,0) -> 0.066535373
A18: 45658 | B18: =SUMIFS(Raw_Data!$I:$I,Raw_Data!$A:$A,A18) -> 581590.94 | C18: =SUMIFS(Raw_Data!$U:$U,Raw_Data!$A:$A,A18) -> 614448.06 | D18: =B18-C18 -> -32857.12 | E18: =IFERROR(D18/C18,0) -> -0.053474203 | F18: =IFERROR((B18-B17)/B17,0) -> -0.063986123
... A29: 45992 | B29: =SUMIFS(Raw_Data!$I:$I,Raw_Data!$A:$A,A29) -> 714236.57 | C29: =SUMIFS(Raw_Data!$U:$U,Raw_Data!$A:$A,A29) -> 709582.28 | D29: =B29-C29 -> 4654.29 | E29: =IFERROR(D29/C29,0) -> 0.0065591971 | F29: =IFERROR((B29-B28)/B28,0) -> 0.058264509
A32: Region-wise Revenue
A33: Region | B33: Total Revenue | C33: Contribution %
A34: North America | B34: =SUMIFS(Raw_Data!$I:$I,Raw_Data!$F:$F,A34) -> 6881817 | C34: =IFERROR(B34/SUM($B$34:$B$36),0) -> 0.47129108
A35: Europe | B35: =SUMIFS(Raw_Data!$I:$I,Raw_Data!$F:$F,A35) -> 5009856.8 | C35: =IFERROR(B35/SUM($B$34:$B$36),0) -> 0.34309265
A36: APAC | B36: =SUMIFS(Raw_Data!$I:$I,Raw_Data!$F:$F,A36) -> 2710378.5 | C36: =IFERROR(B36/SUM($B$34:$B$36),0) -> 0.18561627
A39: Product-wise Revenue
A40: Product Category | B40: Total Revenue | C40: Contribution %
A41: Core Subscription | B41: =SUMIFS(Raw_Data!$I:$I,Raw_Data!$G:$G,A41) -> 11765540 | C41: =IFERROR(B41/SUM($B$41:$B$43),0) -> 0.80574563
A42: Add-on Services | B42: =SUMIFS(Raw_Data!$I:$I,Raw_Data!$G:$G,A42) -> 1644913.7 | C42: =IFERROR(B42/SUM($B$41:$B$43),0) -> 0.11264949
A43: Professional Services | B43: =SUMIFS(Raw_Data!$I:$I,Raw_Data!$G:$G,A43) -> 1191598.8 | C43: =IFERROR(B43/SUM($B$41:$B$43),0) -> 0.081604887
A46: Department-wise Revenue
A47: Department | B47: Total Revenue | C47: Contribution %
A48: Sales | B48: =SUMIFS(Raw_Data!$I:$I,Raw_Data!$E:$E,A48) -> 11765540 | C48: =IFERROR(B48/SUM($B$48:$B$50),0) -> 0.80574563
A49: Customer Success | B49: =SUMIFS(Raw_Data!$I:$I,Raw_Data!$E:$E,A49) -> 1644913.7 | C49: =IFERROR(B49/SUM($B$48:$B$50),0) -> 0.11264949
A50: Marketing | B50: =SUMIFS(Raw_Data!$I:$I,Raw_Data!$E:$E,A50) -> 1191598.8 | C50: =IFERROR(B50/SUM($B$48:$B$50),0) -> 0.081604887

Sheet Cost_Analysis
A1: Cost Analysis
A3: Monthly Cost Trend
A4: Month | B4: COGS | C4: Operating Expenses | D4: Total Cost | E4: Cost Growth % MoM
A5: 45292 | B5: =SUMIFS(Raw_Data!$J:$J,Raw_Data!$A:$A,A5) -> 142492.09 | C5: =SUMIFS(Raw_Data!$L:$L,Raw_Data!$A:$A,A5) -> 158788.22 | D5: =B5+C5 -> 301280.31 | E5: 0
A6: 45323 | B6: =SUMIFS(Raw_Data!$J:$J,Raw_Data!$A:$A,A6) -> 141711.32 | C6: =SUMIFS(Raw_Data!$L:$L,Raw_Data!$A:$A,A6) -> 162559.7 | D6: =B6+C6 -> 304271.02 | E6: =IFERROR((D6-D5)/D5,0) -> 0.0099266693
A7: 45352 | B7: =SUMIFS(Raw_Data!$J:$J,Raw_Data!$A:$A,A7) -> 140888.49 | C7: =SUMIFS(Raw_Data!$L:$L,Raw_Data!$A:$A,A7) -> 163970.68 | D7: =B7+C7 -> 304859.17 | E7: =IFERROR((D7-D6)/D6,0) -> 0.0019329807
A8: 45383 | B8: =SUMIFS(Raw_Data!$J:$J,Raw_Data!$A:$A,A8) -> 139423.28 | C8: =SUMIFS(Raw_Data!$L:$L,Raw_Data!$A:$A,A8) -> 162759.63 | D8: =B8+C8 -> 302182.91 | E8: =IFERROR((D8-D7)/D7,0) -> -0.0087786764
A9: 45413 | B9: =SUMIFS(Raw_Data!$J:$J,Raw_Data!$A:$A,A9) -> 154364.36 | C9: =SUMIFS(Raw_Data!$L:$L,Raw_Data!$A:$A,A9) -> 154523.67 | D9: =B9+C9 -> 308888.03 | E9: =IFERROR((D9-D8)/D8,0) -> 0.022188945
A10: 45444 | B10: =SUMIFS(Raw_Data!$J:$J,Raw_Data!$A:$A,A10) -> 155406.71 | C10: =SUMIFS(Raw_Data!$L:$L,Raw_Data!$A:$A,A10) -> 166437.71 | D10: =B10+C10 -> 321844.42 | E10: =IFERROR((D10-D9)/D9,0) -> 0.041945264
A11: 45474 | B11: =SUMIFS(Raw_Data!$J:$J,Raw_Data!$A:$A,A11) -> 152827.24 | C11: =SUMIFS(Raw_Data!$L:$L,Raw_Data!$A:$A,A11) -> 173571.59 | D11: =B11+C11 -> 326398.83 | E11: =IFERROR((D11-D10)/D10,0) -> 0.014150968
A12: 45505 | B12: =SUMIFS(Raw_Data!$J:$J,Raw_Data!$A:$A,A12) -> 165324.44 | C12: =SUMIFS(Raw_Data!$L:$L,Raw_Data!$A:$A,A12) -> 168287.48 | D12: =B12+C12 -> 333611.92 | E12: =IFERROR((D12-D11)/D11,0) -> 0.022099007
A13: 45536 | B13: =SUMIFS(Raw_Data!$J:$J,Raw_Data!$A:$A,A13) -> 158060.67 | C13: =SUMIFS(Raw_Data!$L:$L,Raw_Data!$A:$A,A13) -> 180090.54 | D13: =B13+C13 -> 338151.21 | E13: =IFERROR((D13-D12)/D12,0) -> 0.013606498
A14: 45566 | B14: =SUMIFS(Raw_Data!$J:$J,Raw_Data!$A:$A,A14) -> 153117.57 | C14: =SUMIFS(Raw_Data!$L:$L,Raw_Data!$A:$A,A14) -> 174252.71 | D14: =B14+C14 -> 327370.28 | E14: =IFERROR((D14-D13)/D13,0) -> -0.03188198
A15: 45597 | B15: =SUMIFS(Raw_Data!$J:$J,Raw_Data!$A:$A,A15) -> 155739.86 | C15: =SUMIFS(Raw_Data!$L:$L,Raw_Data!$A:$A,A15) -> 188277.11 | D15: =B15+C15 -> 344016.97 | E15: =IFERROR((D15-D14)/D14,0) -> 0.050849729
A16: 45627 | B16: =SUMIFS(Raw_Data!$J:$J,Raw_Data!$A:$A,A16) -> 166546.37 | C16: =SUMIFS(Raw_Data!$L:$L,Raw_Data!$A:$A,A16) -> 180226.39 | D16: =B16+C16 -> 346772.76 | E16: =IFERROR((D16-D15)/D15,0) -> 0.0080106223
A17: 45658 | B17: =SUMIFS(Raw_Data!$J:$J,Raw_Data!$A:$A,A17) -> 148444.21 | C17: =SUMIFS(Raw_Data!$L:$L,Raw_Data!$A:$A,A17) -> 184027.38 | D17: =B17+C17 -> 332471.59 | E17: =IFERROR((D17-D16)/D16,0) -> -0.041240754
... A28: 45992 | B28: =SUMIFS(Raw_Data!$J:$J,Raw_Data!$A:$A,A28) -> 193452.71 | C28: =SUMIFS(Raw_Data!$L:$L,Raw_Data!$A:$A,A28) -> 195428.17 | D28: =B28+C28 -> 388880.88 | E28: =IFERROR((D28-D27)/D27,0) -> -0.0056135606
A31: Department-wise Expenses
A32: Department | B32: COGS | C32: Operating Expenses | D32: Total Cost
A33: Sales | B33: =SUMIFS(Raw_Data!$J:$J,Raw_Data!$E:$E,A33) -> 2797344.8 | C33: =SUMIFS(Raw_Data!$L:$L,Raw_Data!$E:$E,A33) -> 3564383.6 | D33: =B33+C33 -> 6361728.4
A34: Customer Success | B34: =SUMIFS(Raw_Data!$J:$J,Raw_Data!$E:$E,A34) -> 570932.5 | C34: =SUMIFS(Raw_Data!$L:$L,Raw_Data!$E:$E,A34) -> 414487.64 | D34: =B34+C34 -> 985420.14
A35: Marketing | B35: =SUMIFS(Raw_Data!$J:$J,Raw_Data!$E:$E,A35) -> 612271.12 | C35: =SUMIFS(Raw_Data!$L:$L,Raw_Data!$E:$E,A35) -> 400514.88 | D35: =B35+C35 -> 1012786
A38: Budget vs Actual Expense (Monthly)
A39: Month | B39: Actual Expense | C39: Budgeted Expense | D39: Variance ($)
A40: 45292 | B40: =SUMIFS(Raw_Data!$X:$X,Raw_Data!$A:$A,A40) -> 301280.31 | C40: =SUMIFS(Raw_Data!$W:$W,Raw_Data!$A:$A,A40) -> 298390 | D40: =B40-C40 -> 2890.31
A41: 45323 | B41: =SUMIFS(Raw_Data!$X:$X,Raw_Data!$A:$A,A41) -> 304271.02 | C41: =SUMIFS(Raw_Data!$W:$W,Raw_Data!$A:$A,A41) -> 302183.49 | D41: =B41-C41 -> 2087.53
A42: 45352 | B42: =SUMIFS(Raw_Data!$X:$X,Raw_Data!$A:$A,A42) -> 304859.17 | C42: =SUMIFS(Raw_Data!$W:$W,Raw_Data!$A:$A,A42) -> 306029.2 | D42: =B42-C42 -> -1170.03
A43: 45383 | B43: =SUMIFS(Raw_Data!$X:$X,Raw_Data!$A:$A,A43) -> 302182.91 | C43: =SUMIFS(Raw_Data!$W:$W,Raw_Data!$A:$A,A43) -> 309927.83 | D43: =B43-C43 -> -7744.92
A44: 45413 | B44: =SUMIFS(Raw_Data!$X:$X,Raw_Data!$A:$A,A44) -> 308888.03 | C44: =SUMIFS(Raw_Data!$W:$W,Raw_Data!$A:$A,A44) -> 313880.24 | D44: =B44-C44 -> -4992.21
A45: 45444 | B45: =SUMIFS(Raw_Data!$X:$X,Raw_Data!$A:$A,A45) -> 321844.42 | C45: =SUMIFS(Raw_Data!$W:$W,Raw_Data!$A:$A,A45) -> 317887.18 | D45: =B45-C45 -> 3957.24
A46: 45474 | B46: =SUMIFS(Raw_Data!$X:$X,Raw_Data!$A:$A,A46) -> 326398.83 | C46: =SUMIFS(Raw_Data!$W:$W,Raw_Data!$A:$A,A46) -> 321949.48 | D46: =B46-C46 -> 4449.35
A47: 45505 | B47: =SUMIFS(Raw_Data!$X:$X,Raw_Data!$A:$A,A47) -> 333611.92 | C47: =SUMIFS(Raw_Data!$W:$W,Raw_Data!$A:$A,A47) -> 326067.96 | D47: =B47-C47 -> 7543.96
A48: 45536 | B48: =SUMIFS(Raw_Data!$X:$X,Raw_Data!$A:$A,A48) -> 338151.21 | C48: =SUMIFS(Raw_Data!$W:$W,Raw_Data!$A:$A,A48) -> 330243.42 | D48: =B48-C48 -> 7907.79
A49: 45566 | B49: =SUMIFS(Raw_Data!$X:$X,Raw_Data!$A:$A,A49) -> 327370.28 | C49: =SUMIFS(Raw_Data!$W:$W,Raw_Data!$A:$A,A49) -> 334476.72 | D49: =B49-C49 -> -7106.44
A50: 45597 | B50: =SUMIFS(Raw_Data!$X:$X,Raw_Data!$A:$A,A50) -> 344016.97 | C50: =SUMIFS(Raw_Data!$W:$W,Raw_Data!$A:$A,A50) -> 338768.72 | D50: =B50-C50 -> 5248.25
A51: 45627 | B51: =SUMIFS(Raw_Data!$X:$X,Raw_Data!$A:$A,A51) -> 346772.76 | C51: =SUMIFS(Raw_Data!$W:$W,Raw_Data!$A:$A,A51) -> 343120.3 | D51: =B51-C51 -> 3652.46
... A63: 45992 | B63: =SUMIFS(Raw_Data!$X:$X,Raw_Data!$A:$A,A63) -> 388880.88 | C63: =SUMIFS(Raw_Data!$W:$W,Raw_Data!$A:$A,A63) -> 400322.26 | D63: =B63-C63 -> -11441.38

Sheet Profitability
A1: Profitability Analysis
A3: Monthly Profitability Trend
A4: Month | B4: Gross Profit | C4: EBITDA | D4: Net Profit | E4: Gross Margin % | F4: EBITDA Margin % | G4: Net Margin %
A5: 45292 | B5: =SUMIFS(Raw_Data!$K:$K,Raw_Data!$A:$A,A5) -> 362346.6 | C5: =SUMIFS(Raw_Data!$M:$M,Raw_Data!$A:$A,A5) -> 203558.38 | D5: =SUMIFS(Raw_Data!$Q:$Q,Raw_Data!$A:$A,A5) -> 124209.54 | E5: =IFERROR(B5/SUMIFS(Raw_Data!$I:$I,Raw_Data!$A:$A,A5),0) -> 0.71774729 | F5: =IFERROR(C5/SUMIFS(Raw_Data!$I:$I,Raw_Data!$A:$A,A5),0) -> 0.4032147 | G5: =IFERROR(D5/SUMIFS(Raw_Data!$I:$I,Raw_Data!$A:$A,A5),0) -> 0.24603808
A6: 45323 | B6: =SUMIFS(Raw_Data!$K:$K,Raw_Data!$A:$A,A6) -> 382536.84 | C6: =SUMIFS(Raw_Data!$M:$M,Raw_Data!$A:$A,A6) -> 219977.14 | D6: =SUMIFS(Raw_Data!$Q:$Q,Raw_Data!$A:$A,A6) -> 139088.64 | E6: =IFERROR(B6/SUMIFS(Raw_Data!$I:$I,Raw_Data!$A:$A,A6),0) -> 0.72968657 | F6: =IFERROR(C6/SUMIFS(Raw_Data!$I:$I,Raw_Data!$A:$A,A6),0) -> 0.41960498 | G6: =IFERROR(D6/SUMIFS(Raw_Data!$I:$I,Raw_Data!$A:$A,A6),0) -> 0.26531069
A7: 45352 | B7: =SUMIFS(Raw_Data!$K:$K,Raw_Data!$A:$A,A7) -> 384361.72 | C7: =SUMIFS(Raw_Data!$M:$M,Raw_Data!$A:$A,A7) -> 220391.04 | D7: =SUMIFS(Raw_Data!$Q:$Q,Raw_Data!$A:$A,A7) -> 139300.54 | E7: =IFERROR(B7/SUMIFS(Raw_Data!$I:$I,Raw_Data!$A:$A,A7),0) -> 0.73176881 | F7: =IFERROR(C7/SUMIFS(Raw_Data!$I:$I,Raw_Data!$A:$A,A7),0) -> 0.41959248 | G7: =IFERROR(D7/SUMIFS(Raw_Data!$I:$I,Raw_Data!$A:$A,A7),0) -> 0.26520797
A8: 45383 | B8: =SUMIFS(Raw_Data!$K:$K,Raw_Data!$A:$A,A8) -> 392886.91 | C8: =SUMIFS(Raw_Data!$M:$M,Raw_Data!$A:$A,A8) -> 230127.28 | D8: =SUMIFS(Raw_Data!$Q:$Q,Raw_Data!$A:$A,A8) -> 147854.86 | E8: =IFERROR(B8/SUMIFS(Raw_Data!$I:$I,Raw_Data!$A:$A,A8),0) -> 0.73807888 | F8: =IFERROR(C8/SUMIFS(Raw_Data!$I:$I,Raw_Data!$A:$A,A8),0) -> 0.43231801 | G8: =IFERROR(D8/SUMIFS(Raw_Data!$I:$I,Raw_Data!$A:$A,A8),0) -> 0.27776072
A9: 45413 | B9: =SUMIFS(Raw_Data!$K:$K,Raw_Data!$A:$A,A9) -> 411898.73 | C9: =SUMIFS(Raw_Data!$M:$M,Raw_Data!$A:$A,A9) -> 257375.06 | D9: =SUMIFS(Raw_Data!$Q:$Q,Raw_Data!$A:$A,A9) -> 167455.66 | E9: =IFERROR(B9/SUMIFS(Raw_Data!$I:$I,Raw_Data!$A:$A,A9),0) -> 0.72739816 | F9: =IFERROR(C9/SUMIFS(Raw_Data!$I:$I,Raw_Data!$A:$A,A9),0) -> 0.45451499 | G9: =IFERROR(D9/SUMIFS(Raw_Data!$I:$I,Raw_Data!$A:$A,A9),0) -> 0.2957206
A10: 45444 | B10: =SUMIFS(Raw_Data!$K:$K,Raw_Data!$A:$A,A10) -> 409257.31 | C10: =SUMIFS(Raw_Data!$M:$M,Raw_Data!$A:$A,A10) -> 242819.6 | D10: =SUMIFS(Raw_Data!$Q:$Q,Raw_Data!$A:$A,A10) -> 157221.63 | E10: =IFERROR(B10/SUMIFS(Raw_Data!$I:$I,Raw_Data!$A:$A,A10),0) -> 0.72478022 | F10: =IFERROR(C10/SUMIFS(Raw_Data!$I:$I,Raw_Data!$A:$A,A10),0) -> 0.43002492 | G10: =IFERROR(D10/SUMIFS(Raw_Data!$I:$I,Raw_Data!$A:$A,A10),0) -> 0.27843394
A11: 45474 | B11: =SUMIFS(Raw_Data!$K:$K,Raw_Data!$A:$A,A11) -> 395710.24 | C11: =SUMIFS(Raw_Data!$M:$M,Raw_Data!$A:$A,A11) -> 222138.65 | D11: =SUMIFS(Raw_Data!$Q:$Q,Raw_Data!$A:$A,A11) -> 140928.15 | E11: =IFERROR(B11/SUMIFS(Raw_Data!$I:$I,Raw_Data!$A:$A,A11),0) -> 0.72139144 | F11: =IFERROR(C11/SUMIFS(Raw_Data!$I:$I,Raw_Data!$A:$A,A11),0) -> 0.40496531 | G11: =IFERROR(D11/SUMIFS(Raw_Data!$I:$I,Raw_Data!$A:$A,A11),0) -> 0.25691617
A12: 45505 | B12: =SUMIFS(Raw_Data!$K:$K,Raw_Data!$A:$A,A12) -> 413269.38 | C12: =SUMIFS(Raw_Data!$M:$M,Raw_Data!$A:$A,A12) -> 244981.9 | D12: =SUMIFS(Raw_Data!$Q:$Q,Raw_Data!$A:$A,A12) -> 155252.16 | E12: =IFERROR(B12/SUMIFS(Raw_Data!$I:$I,Raw_Data!$A:$A,A12),0) -> 0.71426511 | F12: =IFERROR(C12/SUMIFS(Raw_Data!$I:$I,Raw_Data!$A:$A,A12),0) -> 0.42340912 | G12: =IFERROR(D12/SUMIFS(Raw_Data!$I:$I,Raw_Data!$A:$A,A12),0) -> 0.26832668
A13: 45536 | B13: =SUMIFS(Raw_Data!$K:$K,Raw_Data!$A:$A,A13) -> 431195.32 | C13: =SUMIFS(Raw_Data!$M:$M,Raw_Data!$A:$A,A13) -> 251104.78 | D13: =SUMIFS(Raw_Data!$Q:$Q,Raw_Data!$A:$A,A13) -> 162799.75 | E13: =IFERROR(B13/SUMIFS(Raw_Data!$I:$I,Raw_Data!$A:$A,A13),0) -> 0.7317623 | F13: =IFERROR(C13/SUMIFS(Raw_Data!$I:$I,Raw_Data!$A:$A,A13),0) -> 0.4261387 | G13: =IFERROR(D13/SUMIFS(Raw_Data!$I:$I,Raw_Data!$A:$A,A13),0) -> 0.27628018
A14: 45566 | B14: =SUMIFS(Raw_Data!$K:$K,Raw_Data!$A:$A,A14) -> 413580.5 | C14: =SUMIFS(Raw_Data!$M:$M,Raw_Data!$A:$A,A14) -> 239327.79 | D14: =SUMIFS(Raw_Data!$Q:$Q,Raw_Data!$A:$A,A14) -> 153975.16 | E14: =IFERROR(B14/SUMIFS(Raw_Data!$I:$I,Raw_Data!$A:$A,A14),0) -> 0.7298075 | F14: =IFERROR(C14/SUMIFS(Raw_Data!$I:$I,Raw_Data!$A:$A,A14),0) -> 0.42231975 | G14: =IFERROR(D14/SUMIFS(Raw_Data!$I:$I,Raw_Data!$A:$A,A14),0) -> 0.27170581
A15: 45597 | B15: =SUMIFS(Raw_Data!$K:$K,Raw_Data!$A:$A,A15) -> 426846.19 | C15: =SUMIFS(Raw_Data!$M:$M,Raw_Data!$A:$A,A15) -> 238569.08 | D15: =SUMIFS(Raw_Data!$Q:$Q,Raw_Data!$A:$A,A15) -> 153951.83 | E15: =IFERROR(B15/SUMIFS(Raw_Data!$I:$I,Raw_Data!$A:$A,A15),0) -> 0.73267492 | F15: =IFERROR(C15/SUMIFS(Raw_Data!$I:$I,Raw_Data!$A:$A,A15),0) -> 0.40950016 | G15: =IFERROR(D15/SUMIFS(Raw_Data!$I:$I,Raw_Data!$A:$A,A15),0) -> 0.26425595
A16: 45627 | B16: =SUMIFS(Raw_Data!$K:$K,Raw_Data!$A:$A,A16) -> 454802.26 | C16: =SUMIFS(Raw_Data!$M:$M,Raw_Data!$A:$A,A16) -> 274575.87 | D16: =SUMIFS(Raw_Data!$Q:$Q,Raw_Data!$A:$A,A16) -> 183185.58 | E16: =IFERROR(B16/SUMIFS(Raw_Data!$I:$I,Raw_Data!$A:$A,A16),0) -> 0.73195987 | F16: =IFERROR(C16/SUMIFS(Raw_Data!$I:$I,Raw_Data!$A:$A,A16),0) -> 0.44190307 | G16: =IFERROR(D16/SUMIFS(Raw_Data!$I:$I,Raw_Data!$A:$A,A16),0) -> 0.29481932
... A28: 45992 | B28: =SUMIFS(Raw_Data!$K:$K,Raw_Data!$A:$A,A28) -> 520783.86 | C28: =SUMIFS(Raw_Data!$M:$M,Raw_Data!$A:$A,A28) -> 325355.69 | D28: =SUMIFS(Raw_Data!$Q:$Q,Raw_Data!$A:$A,A28) -> 214192.59 | E28: =IFERROR(B28/SUMIFS(Raw_Data!$I:$I,Raw_Data!$A:$A,A28),0) -> 0.72914757 | F28: =IFERROR(C28/SUMIFS(Raw_Data!$I:$I,Raw_Data!$A:$A,A28),0) -> 0.45552931 | G28: =IFERROR(D28/SUMIFS(Raw_Data!$I:$I,Raw_Data!$A:$A,A28),0) -> 0.29989026
A31: Region-wise Profitability
A32: Region | B32: Gross Profit | C32: EBITDA | D32: Net Profit | E32: Gross Margin % | F32: EBITDA Margin % | G32: Net Margin %
A33: North America | B33: =SUMIFS(Raw_Data!$K:$K,Raw_Data!$F:$F,A33) -> 5123690.7 | C33: =SUMIFS(Raw_Data!$M:$M,Raw_Data!$F:$F,A33) -> 3115556.2 | D33: =SUMIFS(Raw_Data!$Q:$Q,Raw_Data!$F:$F,A33) -> 2063164.1 | E33: =IFERROR(B33/SUMIFS(Raw_Data!$I:$I,Raw_Data!$F:$F,A33),0) -> 0.74452585 | F33: =IFERROR(C33/SUMIFS(Raw_Data!$I:$I,Raw_Data!$F:$F,A33),0) -> 0.4527229 | G33: =IFERROR(D33/SUMIFS(Raw_Data!$I:$I,Raw_Data!$F:$F,A33),0) -> 0.29979932
A34: Europe | B34: =SUMIFS(Raw_Data!$K:$K,Raw_Data!$F:$F,A34) -> 3481999.2 | C34: =SUMIFS(Raw_Data!$M:$M,Raw_Data!$F:$F,A34) -> 1964496.6 | D34: =SUMIFS(Raw_Data!$Q:$Q,Raw_Data!$F:$F,A34) -> 1231223.4 | E34: =IFERROR(B34/SUMIFS(Raw_Data!$I:$I,Raw_Data!$F:$F,A34),0) -> 0.69502969 | F34: =IFERROR(C34/SUMIFS(Raw_Data!$I:$I,Raw_Data!$F:$F,A34),0) -> 0.3921263 | G34: =IFERROR(D34/SUMIFS(Raw_Data!$I:$I,Raw_Data!$F:$F,A34),0) -> 0.24576019
A35: APAC | B35: =SUMIFS(Raw_Data!$K:$K,Raw_Data!$F:$F,A35) -> 2015814 | C35: =SUMIFS(Raw_Data!$M:$M,Raw_Data!$F:$F,A35) -> 1162065 | D35: =SUMIFS(Raw_Data!$Q:$Q,Raw_Data!$F:$F,A35) -> 745143.79 | E35: =IFERROR(B35/SUMIFS(Raw_Data!$I:$I,Raw_Data!$F:$F,A35),0) -> 0.74373893 | F35: =IFERROR(C35/SUMIFS(Raw_Data!$I:$I,Raw_Data!$F:$F,A35),0) -> 0.4287464 | G35: =IFERROR(D35/SUMIFS(Raw_Data!$I:$I,Raw_Data!$F:$F,A35),0) -> 0.27492241
A38: Product-wise Profitability
A39: Product Category | B39: Gross Profit | C39: EBITDA | D39: Net Profit | E39: Gross Margin % | F39: EBITDA Margin % | G39: Net Margin %
A40: Core Subscription | B40: =SUMIFS(Raw_Data!$K:$K,Raw_Data!$G:$G,A40) -> 8968195 | C40: =SUMIFS(Raw_Data!$M:$M,Raw_Data!$G:$G,A40) -> 5403811.4 | D40: =SUMIFS(Raw_Data!$Q:$Q,Raw_Data!$G:$G,A40) -> 3597903.6 | E40: =IFERROR(B40/SUMIFS(Raw_Data!$I:$I,Raw_Data!$G:$G,A40),0) -> 0.76224254 | F40: =IFERROR(C40/SUMIFS(Raw_Data!$I:$I,Raw_Data!$G:$G,A40),0) -> 0.45929141 | G40: =IFERROR(D40/SUMIFS(Raw_Data!$I:$I,Raw_Data!$G:$G,A40),0) -> 0.30580013
A41: Add-on Services | B41: =SUMIFS(Raw_Data!$K:$K,Raw_Data!$G:$G,A41) -> 1073981.2 | C41: =SUMIFS(Raw_Data!$M:$M,Raw_Data!$G:$G,A41) -> 659493.56 | D41: =SUMIFS(Raw_Data!$Q:$Q,Raw_Data!$G:$G,A41) -> 399292.12 | E41: =IFERROR(B41/SUMIFS(Raw_Data!$I:$I,Raw_Data!$G:$G,A41),0) -> 0.65291036 | F41: =IFERROR(C41/SUMIFS(Raw_Data!$I:$I,Raw_Data!$G:$G,A41),0) -> 0.40092897 | G41: =IFERROR(D41/SUMIFS(Raw_Data!$I:$I,Raw_Data!$G:$G,A41),0) -> 0.24274351
A42: Professional Services | B42: =SUMIFS(Raw_Data!$K:$K,Raw_Data!$G:$G,A42) -> 579327.71 | C42: =SUMIFS(Raw_Data!$M:$M,Raw_Data!$G:$G,A42) -> 178812.83 | D42: =SUMIFS(Raw_Data!$Q:$Q,Raw_Data!$G:$G,A42) -> 42335.44 | E42: =IFERROR(B42/SUMIFS(Raw_Data!$I:$I,Raw_Data!$G:$G,A42),0) -> 0.4861768 | F42: =IFERROR(C42/SUMIFS(Raw_Data!$I:$I,Raw_Data!$G:$G,A42),0) -> 0.15006127 | G42: =IFERROR(D42/SUMIFS(Raw_Data!$I:$I,Raw_Data!$G:$G,A42),0) -> 0.035528266

Sheet Budget_vs_Actual
A1: Budget vs Actual Analysis
A3: Monthly Variance
A4: Month | B4: Actual Revenue | C4: Budgeted Revenue | D4: Revenue Variance % | E4: Actual Expense | F4: Budgeted Expense | G4: Expense Variance % | H4: Status
A5: 45292 | B5: =SUMIFS(Raw_Data!$V:$V,Raw_Data!$A:$A,A5) -> 504838.69 | C5: =SUMIFS(Raw_Data!$U:$U,Raw_Data!$A:$A,A5) -> 526000 | D5: =IFERROR((B5-C5)/C5,0) -> -0.040230627 | E5: =SUMIFS(Raw_Data!$X:$X,Raw_Data!$A:$A,A5) -> 301280.31 | F5: =SUMIFS(Raw_Data!$W:$W,Raw_Data!$A:$A,A5) -> 298390 | G5: =IFERROR((E5-F5)/F5,0) -> 0.0096863501 | H5: =IF(AND(D5>=0,G5<=0),"Favorable",IF(AND(D5<0,G5>0),"Unfavorable","Mixed")) -> Unfavorable
A6: 45323 | B6: =SUMIFS(Raw_Data!$V:$V,Raw_Data!$A:$A,A6) -> 524248.16 | C6: =SUMIFS(Raw_Data!$U:$U,Raw_Data!$A:$A,A6) -> 532823 | D6: =IFERROR((B6-C6)/C6,0) -> -0.016093224 | E6: =SUMIFS(Raw_Data!$X:$X,Raw_Data!$A:$A,A6) -> 304271.02 | F6: =SUMIFS(Raw_Data!$W:$W,Raw_Data!$A:$A,A6) -> 302183.49 | G6: =IFERROR((E6-F6)/F6,0) -> 0.0069081537 | H6: =IF(AND(D6>=0,G6<=0),"Favorable",IF(AND(D6<0,G6>0),"Unfavorable","Mixed")) -> Unfavorable
A7: 45352 | B7: =SUMIFS(Raw_Data!$V:$V,Raw_Data!$A:$A,A7) -> 525250.21 | C7: =SUMIFS(Raw_Data!$U:$U,Raw_Data!$A:$A,A7) -> 539740.74 | D7: =IFERROR((B7-C7)/C7,0) -> -0.026847204 | E7: =SUMIFS(Raw_Data!$X:$X,Raw_Data!$A:$A,A7) -> 304859.17 | F7: =SUMIFS(Raw_Data!$W:$W,Raw_Data!$A:$A,A7) -> 306029.2 | G7: =IFERROR((E7-F7)/F7,0) -> -0.0038232626 | H7: =IF(AND(D7>=0,G7<=0),"Favorable",IF(AND(D7<0,G7>0),"Unfavorable","Mixed")) -> Mixed
A8: 45383 | B8: =SUMIFS(Raw_Data!$V:$V,Raw_Data!$A:$A,A8) -> 532310.19 | C8: =SUMIFS(Raw_Data!$U:$U,Raw_Data!$A:$A,A8) -> 546754.65 | D8: =IFERROR((B8-C8)/C8,0) -> -0.026418541 | E8: =SUMIFS(Raw_Data!$X:$X,Raw_Data!$A:$A,A8) -> 302182.91 | F8: =SUMIFS(Raw_Data!$W:$W,Raw_Data!$A:$A,A8) -> 309927.83 | G8: =IFERROR((E8-F8)/F8,0) -> -0.024989431 | H8: =IF(AND(D8>=0,G8<=0),"Favorable",IF(AND(D8<0,G8>0),"Unfavorable","Mixed")) -> Mixed
A9: 45413 | B9: =SUMIFS(Raw_Data!$V:$V,Raw_Data!$A:$A,A9) -> 566263.09 | C9: =SUMIFS(Raw_Data!$U:$U,Raw_Data!$A:$A,A9) -> 553866.1 | D9: =IFERROR((B9-C9)/C9,0) -> 0.022382648 | E9: =SUMIFS(Raw_Data!$X:$X,Raw_Data!$A:$A,A9) -> 308888.03 | F9: =SUMIFS(Raw_Data!$W:$W,Raw_Data!$A:$A,A9) -> 313880.24 | G9: =IFERROR((E9-F9)/F9,0) -> -0.015904824 | H9: =IF(AND(D9>=0,G9<=0),"Favorable",IF(AND(D9<0,G9>0),"Unfavorable","Mixed")) -> Favorable
A10: 45444 | B10: =SUMIFS(Raw_Data!$V:$V,Raw_Data!$A:$A,A10) -> 564664.02 | C10: =SUMIFS(Raw_Data!$U:$U,Raw_Data!$A:$A,A10) -> 561076.56 | D10: =IFERROR((B10-C10)/C10,0) -> 0.0063938868 | E10: =SUMIFS(Raw_Data!$X:$X,Raw_Data!$A:$A,A10) -> 321844.42 | F10: =SUMIFS(Raw_Data!$W:$W,Raw_Data!$A:$A,A10) -> 317887.18 | G10: =IFERROR((E10-F10)/F10,0) -> 0.012448567 | H10: =IF(AND(D10>=0,G10<=0),"Favorable",IF(AND(D10<0,G10>0),"Unfavorable","Mixed")) -> Mixed
A11: 45474 | B11: =SUMIFS(Raw_Data!$V:$V,Raw_Data!$A:$A,A11) -> 548537.48 | C11: =SUMIFS(Raw_Data!$U:$U,Raw_Data!$A:$A,A11) -> 568387.51 | D11: =IFERROR((B11-C11)/C11,0) -> -0.03492341 | E11: =SUMIFS(Raw_Data!$X:$X,Raw_Data!$A:$A,A11) -> 326398.83 | F11: =SUMIFS(Raw_Data!$W:$W,Raw_Data!$A:$A,A11) -> 321949.48 | G11: =IFERROR((E11-F11)/F11,0) -> 0.013820025 | H11: =IF(AND(D11>=0,G11<=0),"Favorable",IF(AND(D11<0,G11>0),"Unfavorable","Mixed")) -> Unfavorable
A12: 45505 | B12: =SUMIFS(Raw_Data!$V:$V,Raw_Data!$A:$A,A12) -> 578593.82 | C12: =SUMIFS(Raw_Data!$U:$U,Raw_Data!$A:$A,A12) -> 575800.41 | D12: =IFERROR((B12-C12)/C12,0) -> 0.0048513512 | E12: =SUMIFS(Raw_Data!$X:$X,Raw_Data!$A:$A,A12) -> 333611.92 | F12: =SUMIFS(Raw_Data!$W:$W,Raw_Data!$A:$A,A12) -> 326067.96 | G12: =IFERROR((E12-F12)/F12,0) -> 0.023136158 | H12: =IF(AND(D12>=0,G12<=0),"Favorable",IF(AND(D12<0,G12>0),"Unfavorable","Mixed")) -> Mixed
A13: 45536 | B13: =SUMIFS(Raw_Data!$V:$V,Raw_Data!$A:$A,A13) -> 589255.99 | C13: =SUMIFS(Raw_Data!$U:$U,Raw_Data!$A:$A,A13) -> 583316.78 | D13: =IFERROR((B13-C13)/C13,0) -> 0.010181792 | E13: =SUMIFS(Raw_Data!$X:$X,Raw_Data!$A:$A,A13) -> 338151.21 | F13: =SUMIFS(Raw_Data!$W:$W,Raw_Data!$A:$A,A13) -> 330243.42 | G13: =IFERROR((E13-F13)/F13,0) -> 0.023945337 | H13: =IF(AND(D13>=0,G13<=0),"Favorable",IF(AND(D13<0,G13>0),"Unfavorable","Mixed")) -> Mixed
A14: 45566 | B14: =SUMIFS(Raw_Data!$V:$V,Raw_Data!$A:$A,A14) -> 566698.07 | C14: =SUMIFS(Raw_Data!$U:$U,Raw_Data!$A:$A,A14) -> 590938.16 | D14: =IFERROR((B14-C14)/C14,0) -> -0.041019673 | E14: =SUMIFS(Raw_Data!$X:$X,Raw_Data!$A:$A,A14) -> 327370.28 | F14: =SUMIFS(Raw_Data!$W:$W,Raw_Data!$A:$A,A14) -> 334476.72 | G14: =IFERROR((E14-F14)/F14,0) -> -0.021246441 | H14: =IF(AND(D14>=0,G14<=0),"Favorable",IF(AND(D14<0,G14>0),"Unfavorable","Mixed")) -> Mixed
A15: 45597 | B15: =SUMIFS(Raw_Data!$V:$V,Raw_Data!$A:$A,A15) -> 582586.05 | C15: =SUMIFS(Raw_Data!$U:$U,Raw_Data!$A:$A,A15) -> 598666.1 | D15: =IFERROR((B15-C15)/C15,0) -> -0.026859797 | E15: =SUMIFS(Raw_Data!$X:$X,Raw_Data!$A:$A,A15) -> 344016.97 | F15: =SUMIFS(Raw_Data!$W:$W,Raw_Data!$A:$A,A15) -> 338768.72 | G15: =IFERROR((E15-F15)/F15,0) -> 0.015492133 | H15: =IF(AND(D15>=0,G15<=0),"Favorable",IF(AND(D15<0,G15>0),"Unfavorable","Mixed")) -> Unfavorable
A16: 45627 | B16: =SUMIFS(Raw_Data!$V:$V,Raw_Data!$A:$A,A16) -> 621348.63 | C16: =SUMIFS(Raw_Data!$U:$U,Raw_Data!$A:$A,A16) -> 606502.2 | D16: =IFERROR((B16-C16)/C16,0) -> 0.024478774 | E16: =SUMIFS(Raw_Data!$X:$X,Raw_Data!$A:$A,A16) -> 346772.76 | F16: =SUMIFS(Raw_Data!$W:$W,Raw_Data!$A:$A,A16) -> 343120.3 | G16: =IFERROR((E16-F16)/F16,0) -> 0.010644838 | H16: =IF(AND(D16>=0,G16<=0),"Favorable",IF(AND(D16<0,G16>0),"Unfavorable","Mixed")) -> Mixed
... A28: 45992 | B28: =SUMIFS(Raw_Data!$V:$V,Raw_Data!$A:$A,A28) -> 714236.57 | C28: =SUMIFS(Raw_Data!$U:$U,Raw_Data!$A:$A,A28) -> 709582.28 | D28: =IFERROR((B28-C28)/C28,0) -> 0.0065591971 | E28: =SUMIFS(Raw_Data!$X:$X,Raw_Data!$A:$A,A28) -> 388880.88 | F28: =SUMIFS(Raw_Data!$W:$W,Raw_Data!$A:$A,A28) -> 400322.26 | G28: =IFERROR((E28-F28)/F28,0) -> -0.028580424 | H28: =IF(AND(D28>=0,G28<=0),"Favorable",IF(AND(D28<0,G28>0),"Unfavorable","Mixed")) -> Favorable
A31: Quarterly Variance Summary
A32: Quarter | B32: Revenue Variance ($) | C32: Expense Variance ($)
A33: 2024 Q1 | B33: =SUMIFS(Raw_Data!$V:$V,Raw_Data!$D:$D,2024,Raw_Data!$C:$C,"Q1")-SUMIFS(Raw_Data!$U:$U,Raw_Data!$D:$D,2024,Raw_Data!$C:$C,"Q1") -> -44226.68 | C33: =SUMIFS(Raw_Data!$X:$X,Raw_Data!$D:$D,2024,Raw_Data!$C:$C,"Q1")-SUMIFS(Raw_Data!$W:$W,Raw_Data!$D:$D,2024,Raw_Data!$C:$C,"Q1") -> 3807.81
A34: 2024 Q2 | B34: =SUMIFS(Raw_Data!$V:$V,Raw_Data!$D:$D,2024,Raw_Data!$C:$C,"Q2")-SUMIFS(Raw_Data!$U:$U,Raw_Data!$D:$D,2024,Raw_Data!$C:$C,"Q2") -> 1539.99 | C34: =SUMIFS(Raw_Data!$X:$X,Raw_Data!$D:$D,2024,Raw_Data!$C:$C,"Q2")-SUMIFS(Raw_Data!$W:$W,Raw_Data!$D:$D,2024,Raw_Data!$C:$C,"Q2") -> -8779.89
A35: 2024 Q3 | B35: =SUMIFS(Raw_Data!$V:$V,Raw_Data!$D:$D,2024,Raw_Data!$C:$C,"Q3")-SUMIFS(Raw_Data!$U:$U,Raw_Data!$D:$D,2024,Raw_Data!$C:$C,"Q3") -> -11117.41 | C35: =SUMIFS(Raw_Data!$X:$X,Raw_Data!$D:$D,2024,Raw_Data!$C:$C,"Q3")-SUMIFS(Raw_Data!$W:$W,Raw_Data!$D:$D,2024,Raw_Data!$C:$C,"Q3") -> 19901.1
A36: 2024 Q4 | B36: =SUMIFS(Raw_Data!$V:$V,Raw_Data!$D:$D,2024,Raw_Data!$C:$C,"Q4")-SUMIFS(Raw_Data!$U:$U,Raw_Data!$D:$D,2024,Raw_Data!$C:$C,"Q4") -> -25473.71 | C36: =SUMIFS(Raw_Data!$X:$X,Raw_Data!$D:$D,2024,Raw_Data!$C:$C,"Q4")-SUMIFS(Raw_Data!$W:$W,Raw_Data!$D:$D,2024,Raw_Data!$C:$C,"Q4") -> 1794.27
A37: 2025 Q1 | B37: =SUMIFS(Raw_Data!$V:$V,Raw_Data!$D:$D,2025,Raw_Data!$C:$C,"Q1")-SUMIFS(Raw_Data!$U:$U,Raw_Data!$D:$D,2025,Raw_Data!$C:$C,"Q1") -> 18558.51 | C37: =SUMIFS(Raw_Data!$X:$X,Raw_Data!$D:$D,2025,Raw_Data!$C:$C,"Q1")-SUMIFS(Raw_Data!$W:$W,Raw_Data!$D:$D,2025,Raw_Data!$C:$C,"Q1") -> 18339
A38: 2025 Q2 | B38: =SUMIFS(Raw_Data!$V:$V,Raw_Data!$D:$D,2025,Raw_Data!$C:$C,"Q2")-SUMIFS(Raw_Data!$U:$U,Raw_Data!$D:$D,2025,Raw_Data!$C:$C,"Q2") -> 7931.17 | C38: =SUMIFS(Raw_Data!$X:$X,Raw_Data!$D:$D,2025,Raw_Data!$C:$C,"Q2")-SUMIFS(Raw_Data!$W:$W,Raw_Data!$D:$D,2025,Raw_Data!$C:$C,"Q2") -> 373.33
A39: 2025 Q3 | B39: =SUMIFS(Raw_Data!$V:$V,Raw_Data!$D:$D,2025,Raw_Data!$C:$C,"Q3")-SUMIFS(Raw_Data!$U:$U,Raw_Data!$D:$D,2025,Raw_Data!$C:$C,"Q3") -> -32171.53 | C39: =SUMIFS(Raw_Data!$X:$X,Raw_Data!$D:$D,2025,Raw_Data!$C:$C,"Q3")-SUMIFS(Raw_Data!$W:$W,Raw_Data!$D:$D,2025,Raw_Data!$C:$C,"Q3") -> 7121.53
A40: 2025 Q4 | B40: =SUMIFS(Raw_Data!$V:$V,Raw_Data!$D:$D,2025,Raw_Data!$C:$C,"Q4")-SUMIFS(Raw_Data!$U:$U,Raw_Data!$D:$D,2025,Raw_Data!$C:$C,"Q4") -> -27740.76 | C40: =SUMIFS(Raw_Data!$X:$X,Raw_Data!$D:$D,2025,Raw_Data!$C:$C,"Q4")-SUMIFS(Raw_Data!$W:$W,Raw_Data!$D:$D,2025,Raw_Data!$C:$C,"Q4") -> -5348.55
A43: Department-wise Revenue Variance
A44: Department | B44: Actual Revenue | C44: Budgeted Revenue
A45: Sales | B45: =SUMIFS(Raw_Data!$V:$V,Raw_Data!$E:$E,A45) -> 11765540 | C45: =SUMIFS(Raw_Data!$U:$U,Raw_Data!$E:$E,A45) -> 11844791
A46: Customer Success | B46: =SUMIFS(Raw_Data!$V:$V,Raw_Data!$E:$E,A46) -> 1644913.7 | C46: =SUMIFS(Raw_Data!$U:$U,Raw_Data!$E:$E,A46) -> 1672354.8
A47: Marketing | B47: =SUMIFS(Raw_Data!$V:$V,Raw_Data!$E:$E,A47) -> 1191598.8 | C47: =SUMIFS(Raw_Data!$U:$U,Raw_Data!$E:$E,A47) -> 1197606.5

Sheet Working_Capital
A1: Working Capital Analysis
A3: Monthly Working Capital & Liquidity
A4: Month | B4: Accounts Receivable | C4: Accounts Payable | D4: Cash Balance | E4: Working Capital | F4: DSO (days) | G4: DPO (days)
A5: 45292 | B5: =SUMIFS(Raw_Data!$Z:$Z,Raw_Data!$A:$A,A5) -> 769023.38 | C5: =SUMIFS(Raw_Data!$AA:$AA,Raw_Data!$A:$A,A5) -> 181828.49 | D5: =SUMIFS(Raw_Data!$AB:$AB,Raw_Data!$A:$A,A5) -> 1120383.8 | E5: =B5-C5 -> 587194.89 | F5: =IFERROR(B5/SUMIFS(Raw_Data!$I:$I,Raw_Data!$A:$A,A5)*30,0) -> 45.699155 | G5: =IFERROR(C5/SUMIFS(Raw_Data!$J:$J,Raw_Data!$A:$A,A5)*30,0) -> 38.281807
A6: 45323 | B6: =SUMIFS(Raw_Data!$Z:$Z,Raw_Data!$A:$A,A6) -> 781434.88 | C6: =SUMIFS(Raw_Data!$AA:$AA,Raw_Data!$A:$A,A6) -> 187793.68 | D6: =SUMIFS(Raw_Data!$AB:$AB,Raw_Data!$A:$A,A6) -> 1137300.5 | E6: =B6-C6 -> 593641.2 | F6: =IFERROR(B6/SUMIFS(Raw_Data!$I:$I,Raw_Data!$A:$A,A6)*30,0) -> 44.717461 | G6: =IFERROR(C6/SUMIFS(Raw_Data!$J:$J,Raw_Data!$A:$A,A6)*30,0) -> 39.755542
A7: 45352 | B7: =SUMIFS(Raw_Data!$Z:$Z,Raw_Data!$A:$A,A7) -> 797888.76 | C7: =SUMIFS(Raw_Data!$AA:$AA,Raw_Data!$A:$A,A7) -> 187533.68 | D7: =SUMIFS(Raw_Data!$AB:$AB,Raw_Data!$A:$A,A7) -> 1140145.4 | E7: =B7-C7 -> 610355.08 | F7: =IFERROR(B7/SUMIFS(Raw_Data!$I:$I,Raw_Data!$A:$A,A7)*30,0) -> 45.571924 | G7: =IFERROR(C7/SUMIFS(Raw_Data!$J:$J,Raw_Data!$A:$A,A7)*30,0) -> 39.932364
A8: 45383 | B8: =SUMIFS(Raw_Data!$Z:$Z,Raw_Data!$A:$A,A8) -> 817565.94 | C8: =SUMIFS(Raw_Data!$AA:$AA,Raw_Data!$A:$A,A8) -> 190418.46 | D8: =SUMIFS(Raw_Data!$AB:$AB,Raw_Data!$A:$A,A8) -> 1138198 | E8: =B8-C8 -> 627147.48 | F8: =IFERROR(B8/SUMIFS(Raw_Data!$I:$I,Raw_Data!$A:$A,A8)*30,0) -> 46.076477 | G8: =IFERROR(C8/SUMIFS(Raw_Data!$J:$J,Raw_Data!$A:$A,A8)*30,0) -> 40.97274
A9: 45413 | B9: =SUMIFS(Raw_Data!$Z:$Z,Raw_Data!$A:$A,A9) -> 863544.6 | C9: =SUMIFS(Raw_Data!$AA:$AA,Raw_Data!$A:$A,A9) -> 178662.85 | D9: =SUMIFS(Raw_Data!$AB:$AB,Raw_Data!$A:$A,A9) -> 1142191.3 | E9: =B9-C9 -> 684881.75 | F9: =IFERROR(B9/SUMIFS(Raw_Data!$I:$I,Raw_Data!$A:$A,A9)*30,0) -> 45.74965 | G9: =IFERROR(C9/SUMIFS(Raw_Data!$J:$J,Raw_Data!$A:$A,A9)*30,0) -> 34.722299
A10: 45444 | B10: =SUMIFS(Raw_Data!$Z:$Z,Raw_Data!$A:$A,A10) -> 862117.26 | C10: =SUMIFS(Raw_Data!$AA:$AA,Raw_Data!$A:$A,A10) -> 194757.16 | D10: =SUMIFS(Raw_Data!$AB:$AB,Raw_Data!$A:$A,A10) -> 1161021.8 | E10: =B10-C10 -> 667360.1 | F10: =IFERROR(B10/SUMIFS(Raw_Data!$I:$I,Raw_Data!$A:$A,A10)*30,0) -> 45.803375 | G10: =IFERROR(C10/SUMIFS(Raw_Data!$J:$J,Raw_Data!$A:$A,A10)*30,0) -> 37.596284
A11: 45474 | B11: =SUMIFS(Raw_Data!$Z:$Z,Raw_Data!$A:$A,A11) -> 827846.21 | C11: =SUMIFS(Raw_Data!$AA:$AA,Raw_Data!$A:$A,A11) -> 205092.82 | D11: =SUMIFS(Raw_Data!$AB:$AB,Raw_Data!$A:$A,A11) -> 1153232.4 | E11: =B11-C11 -> 622753.39 | F11: =IFERROR(B11/SUMIFS(Raw_Data!$I:$I,Raw_Data!$A:$A,A11)*30,0) -> 45.275642 | G11: =IFERROR(C11/SUMIFS(Raw_Data!$J:$J,Raw_Data!$A:$A,A11)*30,0) -> 40.259738
A12: 45505 | B12: =SUMIFS(Raw_Data!$Z:$Z,Raw_Data!$A:$A,A12) -> 875385.37 | C12: =SUMIFS(Raw_Data!$AA:$AA,Raw_Data!$A:$A,A12) -> 199370.32 | D12: =SUMIFS(Raw_Data!$AB:$AB,Raw_Data!$A:$A,A12) -> 1170540.3 | E12: =B12-C12 -> 676015.05 | F12: =IFERROR(B12/SUMIFS(Raw_Data!$I:$I,Raw_Data!$A:$A,A12)*30,0) -> 45.388596 | G12: =IFERROR(C12/SUMIFS(Raw_Data!$J:$J,Raw_Data!$A:$A,A12)*30,0) -> 36.178012
A13: 45536 | B13: =SUMIFS(Raw_Data!$Z:$Z,Raw_Data!$A:$A,A13) -> 890394.33 | C13: =SUMIFS(Raw_Data!$AA:$AA,Raw_Data!$A:$A,A13) -> 214419.39 | D13: =SUMIFS(Raw_Data!$AB:$AB,Raw_Data!$A:$A,A13) -> 1190334.1 | E13: =B13-C13 -> 675974.94 | F13: =IFERROR(B13/SUMIFS(Raw_Data!$I:$I,Raw_Data!$A:$A,A13)*30,0) -> 45.331452 | G13: =IFERROR(C13/SUMIFS(Raw_Data!$J:$J,Raw_Data!$A:$A,A13)*30,0) -> 40.696915
A14: 45566 | B14: =SUMIFS(Raw_Data!$Z:$Z,Raw_Data!$A:$A,A14) -> 832360.06 | C14: =SUMIFS(Raw_Data!$AA:$AA,Raw_Data!$A:$A,A14) -> 200275.75 | D14: =SUMIFS(Raw_Data!$AB:$AB,Raw_Data!$A:$A,A14) -> 1190635.8 | E14: =B14-C14 -> 632084.31 | F14: =IFERROR(B14/SUMIFS(Raw_Data!$I:$I,Raw_Data!$A:$A,A14)*30,0) -> 44.063679 | G14: =IFERROR(C14/SUMIFS(Raw_Data!$J:$J,Raw_Data!$A:$A,A14)*30,0) -> 39.239602
A15: 45597 | B15: =SUMIFS(Raw_Data!$Z:$Z,Raw_Data!$A:$A,A15) -> 887025.67 | C15: =SUMIFS(Raw_Data!$AA:$AA,Raw_Data!$A:$A,A15) -> 219530.7 | D15: =SUMIFS(Raw_Data!$AB:$AB,Raw_Data!$A:$A,A15) -> 1195665.6 | E15: =B15-C15 -> 667494.97 | F15: =IFERROR(B15/SUMIFS(Raw_Data!$I:$I,Raw_Data!$A:$A,A15)*30,0) -> 45.676978 | G15: =IFERROR(C15/SUMIFS(Raw_Data!$J:$J,Raw_Data!$A:$A,A15)*30,0) -> 42.28796
A16: 45627 | B16: =SUMIFS(Raw_Data!$Z:$Z,Raw_Data!$A:$A,A16) -> 921224.53 | C16: =SUMIFS(Raw_Data!$AA:$AA,Raw_Data!$A:$A,A16) -> 209937.75 | D16: =SUMIFS(Raw_Data!$AB:$AB,Raw_Data!$A:$A,A16) -> 1173362.9 | E16: =B16-C16 -> 711286.78 | F16: =IFERROR(B16/SUMIFS(Raw_Data!$I:$I,Raw_Data!$A:$A,A16)*30,0) -> 44.47863 | G16: =IFERROR(C16/SUMIFS(Raw_Data!$J:$J,Raw_Data!$A:$A,A16)*30,0) -> 37.81609
... A28: 45992 | B28: =SUMIFS(Raw_Data!$Z:$Z,Raw_Data!$A:$A,A28) -> 1082342.4 | C28: =SUMIFS(Raw_Data!$AA:$AA,Raw_Data!$A:$A,A28) -> 223019.35 | D28: =SUMIFS(Raw_Data!$AB:$AB,Raw_Data!$A:$A,A28) -> 1297380.5 | E28: =B28-C28 -> 859323.06 | F28: =IFERROR(B28/SUMIFS(Raw_Data!$I:$I,Raw_Data!$A:$A,A28)*30,0) -> 45.461509 | G28: =IFERROR(C28/SUMIFS(Raw_Data!$J:$J,Raw_Data!$A:$A,A28)*30,0) -> 34.585096
A31: Collection Efficiency (MoM AR change vs Revenue)
A32: Month | B32: AR Change ($) | C32: AR as % of Revenue
A33: 45292 | B33: 0 | C33: =IFERROR(B5/SUMIFS(Raw_Data!$I:$I,Raw_Data!$A:$A,Working_Capital!A5),0) -> 1.5233052
A34: 45323 | B34: =B6-B5 -> 12411.5 | C34: =IFERROR(B6/SUMIFS(Raw_Data!$I:$I,Raw_Data!$A:$A,Working_Capital!A6),0) -> 1.490582
A35: 45352 | B35: =B7-B6 -> 16453.88 | C35: =IFERROR(B7/SUMIFS(Raw_Data!$I:$I,Raw_Data!$A:$A,Working_Capital!A7),0) -> 1.5190641
A36: 45383 | B36: =B8-B7 -> 19677.18 | C36: =IFERROR(B8/SUMIFS(Raw_Data!$I:$I,Raw_Data!$A:$A,Working_Capital!A8),0) -> 1.5358826
A37: 45413 | B37: =B9-B8 -> 45978.66 | C37: =IFERROR(B9/SUMIFS(Raw_Data!$I:$I,Raw_Data!$A:$A,Working_Capital!A9),0) -> 1.5249883
A38: 45444 | B38: =B10-B9 -> -1427.34 | C38: =IFERROR(B10/SUMIFS(Raw_Data!$I:$I,Raw_Data!$A:$A,Working_Capital!A10),0) -> 1.5267792
A39: 45474 | B39: =B11-B10 -> -34271.05 | C39: =IFERROR(B11/SUMIFS(Raw_Data!$I:$I,Raw_Data!$A:$A,Working_Capital!A11),0) -> 1.5091881
A40: 45505 | B40: =B12-B11 -> 47539.16 | C40: =IFERROR(B12/SUMIFS(Raw_Data!$I:$I,Raw_Data!$A:$A,Working_Capital!A12),0) -> 1.5129532
A41: 45536 | B41: =B13-B12 -> 15008.96 | C41: =IFERROR(B13/SUMIFS(Raw_Data!$I:$I,Raw_Data!$A:$A,Working_Capital!A13),0) -> 1.5110484
A42: 45566 | B42: =B14-B13 -> -58034.27 | C42: =IFERROR(B14/SUMIFS(Raw_Data!$I:$I,Raw_Data!$A:$A,Working_Capital!A14),0) -> 1.4687893
A43: 45597 | B43: =B15-B14 -> 54665.61 | C43: =IFERROR(B15/SUMIFS(Raw_Data!$I:$I,Raw_Data!$A:$A,Working_Capital!A15),0) -> 1.5225659
A44: 45627 | B44: =B16-B15 -> 34198.86 | C44: =IFERROR(B16/SUMIFS(Raw_Data!$I:$I,Raw_Data!$A:$A,Working_Capital!A16),0) -> 1.482621
A45: 45658 | B45: =B17-B16 -> -30478.6 | C45: =IFERROR(B17/SUMIFS(Raw_Data!$I:$I,Raw_Data!$A:$A,Working_Capital!A17),0) -> 1.5315678
... A56: 45992 | B56: =B28-B27 -> 43954.18 | C56: =IFERROR(B28/SUMIFS(Raw_Data!$I:$I,Raw_Data!$A:$A,Working_Capital!A28),0) -> 1.5153836

Sheet KPI_Summary
A1: KPI Summary — FY2024-FY2025
A2: All figures aggregate 24 months across Sales, Customer Success and Marketing segments
A4: Financial KPIs
A5: KPI | B5: Value
A6: Total Revenue | B6: =SUM(Raw_Data!I2:I121) -> 14602052
A7: Revenue Growth % (Jan24 vs Dec25) | B7: =IFERROR((Revenue_Analysis!B29-Revenue_Analysis!B6)/Revenue_Analysis!B6,0) -> 0.41478176
A8: Gross Profit | B8: =SUM(Raw_Data!K2:K121) -> 10621504
A9: Gross Margin % | B9: =IFERROR(B8/B6,0) -> 0.72739802
A10: EBITDA | B10: =SUM(Raw_Data!M2:M121) -> 6242117.8
A11: EBITDA Margin % | B11: =IFERROR(B10/B6,0) -> 0.42748222
A12: Net Profit | B12: =SUM(Raw_Data!Q2:Q121) -> 4039531.2
A13: Net Profit Margin % | B13: =IFERROR(B12/B6,0) -> 0.27664133
A14: Total Operating Expenses | B14: =SUM(Raw_Data!L2:L121) -> 4379386.1
A15: Total Budget Variance (Revenue, $) | B15: =SUM(Raw_Data!Y2:Y121) -> -112700.42
A16: Cash Balance (latest month) | B16: =Working_Capital!D28 -> 1297380.5
A17: Working Capital (latest month) | B17: =Working_Capital!E28 -> 859323.06
A18: Accounts Receivable (latest month) | B18: =Working_Capital!B28 -> 1082342.4
A19: Accounts Payable (latest month) | B19: =Working_Capital!C28 -> 223019.35
A20: DSO - Days Sales Outstanding (latest) | B20: =Working_Capital!F28 -> 45.461509
A21: DPO - Days Payable Outstanding (latest) | B21: =Working_Capital!G28 -> 34.585096
A22: Return on Sales (Net Profit/Revenue) | B22: =IFERROR(B12/B6,0) -> 0.27664133
